custom.py
custompackage01-1.0.0.dist-info/METADATA
custompackage01-1.0.0.dist-info/WHEEL
custompackage01-1.0.0.dist-info/top_level.txt
custompackage01-1.0.0.dist-info/RECORD
