Metadata-Version: 2.1
Name: custompackage01
Version: 1.0.0
Summary: Custom python module
Author: Ananth S S
